twdownloader/__init__.py
twdownloader/telewebion.py
twdownloader-0.3.1.dist-info/LICENSE
twdownloader-0.3.1.dist-info/METADATA
twdownloader-0.3.1.dist-info/WHEEL
twdownloader-0.3.1.dist-info/top_level.txt
twdownloader-0.3.1.dist-info/RECORD
