Metadata-Version: 2.1
Name: twdownloader
Version: 0.3.1
Summary: A package for downloading from Telewebion
Author: hosseinam
Author-email: hoss.rezaei98@gmail.com
Classifier: Programming Language :: Python :: 3
Classifier: License :: OSI Approved :: MIT License
Classifier: Operating System :: OS Independent
Requires-Python: >=3.6
License-File: LICENSE
Requires-Dist: PySocks==1.7.1
Requires-Dist: requests
Requires-Dist: m3u8==2.0.0
